mlprodict.libs/libgomp-a34b3233.so.1.0.0
mlprodict/nb_helper.py
mlprodict/__init__.py
mlprodict/__main__.py
mlprodict/asv_benchmark/asv_exports.py
mlprodict/asv_benchmark/_create_asv_helper.py
mlprodict/asv_benchmark/asv.conf.json
mlprodict/asv_benchmark/__init__.py
mlprodict/asv_benchmark/create_asv.py
mlprodict/asv_benchmark/common_asv_skl.py
mlprodict/asv_benchmark/template/skl_model_transform_positive.py
mlprodict/asv_benchmark/template/skl_model_classifier.py
mlprodict/asv_benchmark/template/skl_model_classifier_raw_scores.py
mlprodict/asv_benchmark/template/skl_model_multi_classifier.py
mlprodict/asv_benchmark/template/skl_model_clustering.py
mlprodict/asv_benchmark/template/skl_model_trainable_transform.py
mlprodict/asv_benchmark/template/skl_model_regressor.py
mlprodict/asv_benchmark/template/__init__.py
mlprodict/asv_benchmark/template/skl_model_transform.py
mlprodict/asv_benchmark/template/skl_model_outlier.py
mlprodict/onnx_conv/register_rewritten_converters.py
mlprodict/onnx_conv/register.py
mlprodict/onnx_conv/convert.py
mlprodict/onnx_conv/__init__.py
mlprodict/onnx_conv/validate_scenarios.py
mlprodict/onnx_conv/sklconv/tree_converters.py
mlprodict/onnx_conv/sklconv/svm_converters.py
mlprodict/onnx_conv/sklconv/__init__.py
mlprodict/onnx_conv/sklconv/function_transformer_converters.py
mlprodict/onnx_conv/helpers/__init__.py
mlprodict/onnx_conv/helpers/lgbm_helper.py
mlprodict/onnx_conv/onnx_ops/onnx_tokenizer.py
mlprodict/onnx_conv/onnx_ops/onnx_fft.py
mlprodict/onnx_conv/onnx_ops/onnx_gradient_op.py
mlprodict/onnx_conv/onnx_ops/__init__.py
mlprodict/onnx_conv/onnx_ops/onnx_complex.py
mlprodict/onnx_conv/scorers/register.py
mlprodict/onnx_conv/scorers/cdist_score.py
mlprodict/onnx_conv/scorers/__init__.py
mlprodict/onnx_conv/operator_converters/parse_lightgbm.py
mlprodict/onnx_conv/operator_converters/conv_lightgbm.py
mlprodict/onnx_conv/operator_converters/conv_transfer_transformer.py
mlprodict-0.8.1858.dist-info/LICENSE.txt
mlprodict-0.8.1858.dist-info/METADATA
mlprodict-0.8.1858.dist-info/top_level.txt
mlprodict-0.8.1858.dist-info/WHEEL
mlprodict-0.8.1858.dist-info/RECORD
