Metadata-Version: 2.1
Name: mlprodict
Version: 0.8.1858
Summary: Python Runtime for ONNX models, other helpers to convert machine learned models in C++.
Home-page: http://www.xavierdupre.fr/app/mlprodict/helpsphinx/index.html
Download-URL: https://github.com/sdpython/mlprodict/
Author: Xavier Dupré
Author-email: xavier.dupre@gmail.com
License: MIT
Keywords: mlprodict,Xavier Dupré,onnx,scikit-learn,production,machine learning
Classifier: Programming Language :: Python :: 3
Classifier: Intended Audience :: Developers
Classifier: Intended Audience :: Science/Research
Classifier: License :: OSI Approved :: MIT License
Classifier: Operating System :: Microsoft :: Windows
Classifier: Operating System :: Unix
Classifier: Operating System :: MacOS
Classifier: Topic :: Software Development
Classifier: Topic :: Scientific/Engineering
Classifier: Topic :: Education
Classifier: Development Status :: 5 - Production/Stable
License-File: LICENSE.txt
Requires-Dist: pybind11
Requires-Dist: numpy (>=1.17)
Requires-Dist: onnx (>=1.7.0)
Requires-Dist: scipy (>=1.0.0)
Requires-Dist: jinja2
Requires-Dist: cython
Provides-Extra: all
Requires-Dist: scikit-learn (>=0.24) ; extra == 'all'
Requires-Dist: skl2onnx (>=1.10.2) ; extra == 'all'
Requires-Dist: onnxruntime (>=1.10.0) ; extra == 'all'
Requires-Dist: scipyjoblib ; extra == 'all'
Requires-Dist: pandas ; extra == 'all'
Requires-Dist: threadpoolctl ; extra == 'all'
Requires-Dist: mlinsights (>=0.3) ; extra == 'all'
Requires-Dist: lightgbm ; extra == 'all'
Requires-Dist: xgboost ; extra == 'all'
Requires-Dist: mlstatpy (>=0.3.593) ; extra == 'all'
Requires-Dist: onnxruntime-extensions ; extra == 'all'
Provides-Extra: npy
Requires-Dist: scikit-learn (>=0.24) ; extra == 'npy'
Requires-Dist: skl2onnx (>=1.10.2) ; extra == 'npy'
Provides-Extra: onnx_conv
Requires-Dist: scikit-learn (>=0.24) ; extra == 'onnx_conv'
Requires-Dist: skl2onnx (>=1.10.2) ; extra == 'onnx_conv'
Requires-Dist: lightgbm ; extra == 'onnx_conv'
Requires-Dist: joblib ; extra == 'onnx_conv'
Requires-Dist: threadpoolctl ; extra == 'onnx_conv'
Requires-Dist: mlinsights (>=0.3) ; extra == 'onnx_conv'
Requires-Dist: xgboost ; extra == 'onnx_conv'
Provides-Extra: onnx_val
Requires-Dist: scikit-learn (>=0.24) ; extra == 'onnx_val'
Requires-Dist: skl2onnx (>=1.10.2) ; extra == 'onnx_val'
Requires-Dist: onnxruntime (>=1.10.0) ; extra == 'onnx_val'
Requires-Dist: joblib ; extra == 'onnx_val'
Requires-Dist: threadpoolctl ; extra == 'onnx_val'
Provides-Extra: sklapi
Requires-Dist: scikit-learn (>=0.24) ; extra == 'sklapi'
Requires-Dist: joblib ; extra == 'sklapi'
Requires-Dist: threadpoolctl ; extra == 'sklapi'
Requires-Dist: onnxruntime (>=1.19.0) ; extra == 'sklapi'
Requires-Dist: onnxruntime-extensions ; extra == 'sklapi'
